odoo/addons/hr_recruitment_notification/README.rst
odoo/addons/hr_recruitment_notification/__init__.py
odoo/addons/hr_recruitment_notification/__manifest__.py
odoo/addons/hr_recruitment_notification/data/message_subtypes.xml
odoo/addons/hr_recruitment_notification/i18n/de.po
odoo/addons/hr_recruitment_notification/i18n/es.po
odoo/addons/hr_recruitment_notification/i18n/hr_recruitment_notification.pot
odoo/addons/hr_recruitment_notification/i18n/it.po
odoo/addons/hr_recruitment_notification/readme/CONTRIBUTORS.rst
odoo/addons/hr_recruitment_notification/readme/DESCRIPTION.rst
odoo/addons/hr_recruitment_notification/readme/ROADMAP.rst
odoo/addons/hr_recruitment_notification/static/description/icon.png
odoo/addons/hr_recruitment_notification/static/description/index.html
odoo/addons/hr_recruitment_notification/tests/__init__.py
odoo/addons/hr_recruitment_notification/tests/test_hr_application_notification.py
odoo14_addon_hr_recruitment_notification-14.0.1.0.1.dist-info/METADATA
odoo14_addon_hr_recruitment_notification-14.0.1.0.1.dist-info/WHEEL
odoo14_addon_hr_recruitment_notification-14.0.1.0.1.dist-info/top_level.txt
odoo14_addon_hr_recruitment_notification-14.0.1.0.1.dist-info/RECORD
